{
  "source_archive": "/home/uglyegg/Repos/! WORKING-in_progress/crushr/PHASE2_RESEARCH/baselines/zip/largefiles.zip",
  "scenario_id": "p2-core-largefiles-zip-byte_overwrite-header-1B-2600",
  "corruption_type": "byte_overwrite",
  "target": "header",
  "magnitude": "1B",
  "seed": 2600,
  "concrete_mutation_details": [
    {
      "operation": "byte_overwrite",
      "offset": 2600,
      "before": 140,
      "after": 27,
      "length": 1,
      "range_start": 2600,
      "range_end": 2601,
      "bit_index": null
    }
  ]
}